climada/__init__.py
climada/_version.py
climada/conf/climada.conf
climada/data/demo/SC22000_VE__M1.grd.gz
climada/data/demo/atl_prob_nonames.mat
climada/data/demo/demo_emdat_impact_data_2020.csv
climada/data/demo/demo_future_TEST.xlsx
climada/data/demo/demo_today.xlsx
climada/data/demo/exp_demo_today.h5
climada/data/demo/fp_lothar_crop-test.nc
climada/data/demo/fp_xynthia_crop-test.nc
climada/data/demo/ibtracs_global_intp-None_1992230N11325.csv
climada/data/demo/nl_rails.gpkg
climada/data/demo/tc_fl_1990_2004.h5
climada/data/demo/earth_engine/dresden.tif
climada/data/demo/earth_engine/population-density_median.tif
climada/data/system/FAOSTAT_data_country_codes.csv
climada/data/system/GDP_TWN_IMF_WEO_data.csv
climada/data/system/GLB_NatID_grid_0360as_adv_2.mat
climada/data/system/NatEarth_Centroids_150as.hdf5
climada/data/system/NatEarth_Centroids_360as.hdf5
climada/data/system/NatID_grid_0150as.nc
climada/data/system/NatRegIDs.csv
climada/data/system/WEALTH2GDP_factors_CRI_2016.csv
climada/data/system/entity_template.xlsx
climada/data/system/hazard_template.xlsx
climada/data/system/rcp_db.xls
climada/data/system/tc_impf_cal_v01_EDR.csv
climada/data/system/tc_impf_cal_v01_RMSF.csv
climada/data/system/tc_impf_cal_v01_TDR1.0.csv
climada/data/system/tc_impf_cal_v01_TDR1.5.csv
climada/data/system/GSDP/AUS_GSDP.xls
climada/data/system/GSDP/BRA_GSDP.xls
climada/data/system/GSDP/CAN_GSDP.xls
climada/data/system/GSDP/CHE_GSDP.xls
climada/data/system/GSDP/CHN_GSDP.xls
climada/data/system/GSDP/DEU_GSDP.xls
climada/data/system/GSDP/FRA_GSDP.xls
climada/data/system/GSDP/IDN_GSDP.xls
climada/data/system/GSDP/IND_GSDP.xls
climada/data/system/GSDP/JPN_GSDP.xls
climada/data/system/GSDP/MEX_GSDP.xls
climada/data/system/GSDP/TUR_GSDP.xls
climada/data/system/GSDP/USA_GSDP.xls
climada/data/system/GSDP/ZAF_GSDP.xls
climada/engine/__init__.py
climada/engine/calibration_opt.py
climada/engine/cost_benefit.py
climada/engine/forecast.py
climada/engine/impact.py
climada/engine/impact_calc.py
climada-6.1.0.dist-info/licenses/AUTHORS.md
climada-6.1.0.dist-info/licenses/LICENSE
climada-6.1.0.dist-info/METADATA
climada-6.1.0.dist-info/WHEEL
climada-6.1.0.dist-info/top_level.txt
climada-6.1.0.dist-info/RECORD
