Metadata-Version: 2.4
Name: climada
Version: 6.1.0
Summary: Framework for climate risk assessment and adaptation option appraisal
Author-email: ETH <climada-info@sympa.ethz.ch>
License: GNU General Public License v3 (GPLv3)
Project-URL: Homepage, https://github.com/CLIMADA-project/climada_python
Keywords: climate,adaptation
Classifier: Development Status :: 4 - Beta
Classifier: Programming Language :: Python :: 3
Classifier: Topic :: Scientific/Engineering :: Atmospheric Science
Classifier: Topic :: Scientific/Engineering :: GIS
Classifier: Topic :: Scientific/Engineering :: Mathematics
Requires-Python: <3.13,>=3.10
License-File: LICENSE
License-File: AUTHORS.md
Requires-Dist: bayesian-optimization
Requires-Dist: bottleneck
Requires-Dist: cartopy
Requires-Dist: cfgrib
Requires-Dist: contextily
Requires-Dist: dask
Requires-Dist: deprecation
Requires-Dist: fiona
Requires-Dist: gdal
Requires-Dist: geopandas
Requires-Dist: h5py
Requires-Dist: haversine
Requires-Dist: matplotlib
Requires-Dist: netcdf4
Requires-Dist: numba
Requires-Dist: openpyxl
Requires-Dist: overpy
Requires-Dist: pandas
Requires-Dist: pathos
Requires-Dist: peewee
Requires-Dist: pillow
Requires-Dist: pint
Requires-Dist: pyarrow
Requires-Dist: pycountry
Requires-Dist: pyproj
Requires-Dist: rasterio
Requires-Dist: salib
Requires-Dist: scikit-learn
Requires-Dist: seaborn
Requires-Dist: sparse
Requires-Dist: statsmodels
Requires-Dist: tables
Requires-Dist: tabulate
Requires-Dist: tqdm
Requires-Dist: xarray
Requires-Dist: xlrd
Requires-Dist: xlsxwriter
Provides-Extra: doc
Requires-Dist: ipython; extra == "doc"
Requires-Dist: myst-nb; extra == "doc"
Requires-Dist: readthedocs-sphinx-ext>=2.2; extra == "doc"
Requires-Dist: sphinx; extra == "doc"
Requires-Dist: sphinx-book-theme; extra == "doc"
Requires-Dist: sphinx-markdown-tables; extra == "doc"
Requires-Dist: sphinx-design; extra == "doc"
Requires-Dist: sphinx-mdinclude; extra == "doc"
Provides-Extra: dev
Requires-Dist: ipython; extra == "dev"
Requires-Dist: mccabe>=0.6; extra == "dev"
Requires-Dist: pylint>=3.0; extra == "dev"
Requires-Dist: pytest; extra == "dev"
Requires-Dist: pytest-cov; extra == "dev"
Requires-Dist: pytest-subtests; extra == "dev"
Requires-Dist: pre-commit; extra == "dev"
Dynamic: license-file
